markpy/__init__.py
markpy/main.py
markpy/types.py
markpy-0.0.1.dist-info/LICENSE
markpy-0.0.1.dist-info/METADATA
markpy-0.0.1.dist-info/WHEEL
markpy-0.0.1.dist-info/entry_points.txt
markpy-0.0.1.dist-info/top_level.txt
markpy-0.0.1.dist-info/RECORD
